{
  "gradation": {
    "linear": [
      {
        "property": "43deg ,#4158D0 0%,#C850C0  46%,#FFCC70 100%",
        "deg": 43,
        "colors": [
          { "color": "#4158D0", "position": 0 },
          { "color": "#C850C0 ", "position": 46 },
          { "color": "#FFCC70", "position": 100 }
        ],
        "fallback": "#4158D0"
      },
      {
        "property": "160deg ,#0093E9 0%,#80D0C7  100%",
        "deg": 160,
        "colors": [
          { "color": "#0093E9", "position": 0 },
          { "color": "#80D0C7 ", "position": 100 }
        ],
        "fallback": "#0093E9"
      },
      {
        "property": "62deg ,#8EC5FC 0%,#E0C3FC  100%",
        "deg": 62,
        "colors": [
          { "color": "#8EC5FC", "position": 0 },
          { "color": "#E0C3FC ", "position": 100 }
        ],
        "fallback": "#0093E9"
      },
      {
        "property": "62deg, #FBAB7E 0%, #F7CE68 100%",
        "deg": 62,
        "colors": [
          { "color": "#FBAB7E", "position": 0 },
          { "color": "#F7CE68 ", "position": 100 }
        ],
        "fallback": "#FBAB7E"
      },
      {
        "property": "45deg, #85FFBD 0%, #FFFB7D 100%",
        "deg": 45,
        "colors": [
          { "color": "#FBAB7E", "position": 0 },
          { "color": "#FFFB7D ", "position": 100 }
        ],
        "fallback": "#85FFBD"
      },
      {
        "property": "135deg, #8BC6EC 0%, #9599E2 100%",
        "deg": 62,
        "colors": [
          { "color": "#8BC6EC", "position": 0 },
          { "color": "#9599E2 ", "position": 100 }
        ],
        "fallback": "#8BC6EC"
      }

    ],
    "radial": [
      {
        "colors": [
          { "color": "#4158D0", "position": 0 },
          { "color": "#C850C0 ", "position": 46 },
          { "color": "#FFCC70", "position": 100 }
        ],
        "fallback": "#4158D0"
      }
    ]
  }
}
